vesper_nighthawk/.DS_Store
vesper_nighthawk/__init__.py
vesper_nighthawk/conda_utils.py
vesper_nighthawk/detector.py
vesper_nighthawk/data/README.txt
vesper_nighthawk/data/species_code_mapping.json
vesper_nighthawk/tests/test_detector.py
vesper_nighthawk-1.0.0.dist-info/METADATA
vesper_nighthawk-1.0.0.dist-info/WHEEL
vesper_nighthawk-1.0.0.dist-info/entry_points.txt
vesper_nighthawk-1.0.0.dist-info/licenses/LICENSE
vesper_nighthawk-1.0.0.dist-info/RECORD
