Metadata-Version: 2.1
Name: vesper-nighthawk
Version: 1.0.0
Summary: Nighthawk NFC detector plugin for Vesper.
Project-URL: Bug Tracker, https://github.com/haroldmills/vesper-nighthawk/issues
Project-URL: Source Code, https://github.com/haroldmills/vesper-nighthawk
Author-email: Harold Mills <harold.mills@gmail.com>
License: MIT License
License-File: LICENSE
Classifier: License :: OSI Approved :: MIT License
Classifier: Operating System :: OS Independent
Classifier: Programming Language :: Python :: 3
Requires-Python: ~=3.10.0
Requires-Dist: numpy
